MANIFEST.in
README.md
setup.py
tests/test_arrays.py
tests/test_dispatch.py
tests/test_ods.py
tests/test_utils.py
xalgorithm/__init__.py
xalgorithm/arrays.py
xalgorithm/cli.py
xalgorithm/decorate.py
xalgorithm/metrics.py
xalgorithm/types.py
xalgorithm/utils.py
xalgorithm.egg-info/PKG-INFO
xalgorithm.egg-info/SOURCES.txt
xalgorithm.egg-info/dependency_links.txt
xalgorithm.egg-info/entry_points.txt
xalgorithm.egg-info/not-zip-safe
xalgorithm.egg-info/top_level.txt
xalgorithm/hpc/__init__.py
xalgorithm/hpc/do_prime.py
xalgorithm/mle/__init__.py
xalgorithm/mle/activate.py
xalgorithm/mle/loss.py
xalgorithm/mle/optim.py
xalgorithm/mle/sl.py
xalgorithm/mle/utils.py
xalgorithm/mle/viz.py
xalgorithm/ods/__init__.py
xalgorithm/ods/array.py
xalgorithm/ods/interface.py
xalgorithm/ods/pwa.py
xalgorithm/ods/rfm.py
xalgorithm/ods/vds.py
xalgorithm/out/__init__.py
xalgorithm/out/ignore_chatgpt.py
xalgorithm/out/magic_cmd.py
xalgorithm/out/pd_rich.py