Metadata-Version: 2.1
Name: xalgorithm
Version: 0.0.5
Summary: My Data Structures and Algorithms Implemented in Python
Home-page: https://github.com/dennislx/xalgorithm
Author: Xiang Liu
Author-email: dennisl@udel.edu
License: MIT
Platform: Linux
